jf_ingest/__init__.py
jf_ingest/adaptive_throttler.py
jf_ingest/config.py
jf_ingest/constants.py
jf_ingest/diagnostics.py
jf_ingest/file_operations.py
jf_ingest/graphql_utils.py
jf_ingest/harness.py
jf_ingest/logging_helper.py
jf_ingest/name_redactor.py
jf_ingest/regression_detector.py
jf_ingest/utils.py
jf_ingest/validation.py
jf_ingest/data_manifests/__init__.py
jf_ingest/data_manifests/manifest_base.py
jf_ingest/data_manifests/jira/__init__.py
jf_ingest/data_manifests/jira/generator.py
jf_ingest/data_manifests/jira/manifest_base.py
jf_ingest/data_manifests/jira/adapters/__init__.py
jf_ingest/data_manifests/jira/adapters/jira_cloud.py
jf_ingest/data_manifests/jira/adapters/manifest_adapter.py
jf_ingest/events/models.py
jf_ingest/events/utils.py
jf_ingest/jf_git/__init__.py
jf_ingest/jf_git/exceptions.py
jf_ingest/jf_git/standardized_models.py
jf_ingest/jf_git/utils.py
jf_ingest/jf_git/adapters/__init__.py
jf_ingest/jf_git/adapters/azure_devops.py
jf_ingest/jf_git/adapters/github.py
jf_ingest/jf_git/adapters/gitlab.py
jf_ingest/jf_git/clients/__init__.py
jf_ingest/jf_git/clients/azure_devops.py
jf_ingest/jf_git/clients/github.py
jf_ingest/jf_git/clients/gitlab.py
jf_ingest/jf_jira/__init__.py
jf_ingest/jf_jira/auth.py
jf_ingest/jf_jira/custom_fields.py
jf_ingest/jf_jira/downloaders.py
jf_ingest/jf_jira/exceptions.py
jf_ingest/jf_jira/utils.py
jf_ingest/telemetry/__init__.py
jf_ingest/telemetry/metrics.py
jf_ingest/telemetry/tracing.py
jf_ingest-0.1.214.dist-info/licenses/LICENSE
jf_ingest-0.1.214.dist-info/METADATA
jf_ingest-0.1.214.dist-info/WHEEL
jf_ingest-0.1.214.dist-info/top_level.txt
jf_ingest-0.1.214.dist-info/RECORD
