Metadata-Version: 2.4
Name: jf-ingest
Version: 0.1.214
Summary: library used for ingesting jira data
Author-email: jellyfish-oss <oss@jellyfish.co>
License: MIT
Project-URL: Homepage, https://github.com/Jellyfish-AI/jf_ingest
Requires-Python: >=3.10
License-File: LICENSE
Requires-Dist: jira[opt]==3.1.1
Requires-Dist: requests-mock==1.11.0
Requires-Dist: pytz>=2023.3.post1
Requires-Dist: psutil>=5.9.6
Requires-Dist: tqdm>=4.66.1
Requires-Dist: python-dateutil>=2.8.2
Requires-Dist: requests>=2.31.0
Requires-Dist: pyjwt>2
Requires-Dist: opentelemetry-distro>=0.38b0
Requires-Dist: opentelemetry-exporter-otlp>=1.17.0
Requires-Dist: python-gitlab>=5.1.0
Dynamic: license-file
